fabrial_oven_control/__init__.py
fabrial_oven_control/constants.py
fabrial_oven_control/oven.py
fabrial_oven_control/quince10GCE.py
fabrial_oven_control/widgets.py
fabrial_oven_control/items/__init__.py
fabrial_oven_control/items/increment_setpoint/__init__.py
fabrial_oven_control/items/increment_setpoint/increment_setpoint_item.py
fabrial_oven_control/items/increment_setpoint/increment_setpoint_step.py
fabrial_oven_control/items/increment_setpoint/increment_setpoint_widget.py
fabrial_oven_control/items/increment_setpoint/thermometer--plus.png
fabrial_oven_control/items/increment_setpoint/descriptions/data_recording.toml
fabrial_oven_control/items/increment_setpoint/descriptions/overview.md
fabrial_oven_control/items/increment_setpoint/descriptions/parameters.toml
fabrial_oven_control/items/increment_setpoint/descriptions/visuals.md
fabrial_oven_control/items/record_setpoint/__init__.py
fabrial_oven_control/items/record_setpoint/record_setpoint_item.py
fabrial_oven_control/items/record_setpoint/record_setpoint_step.py
fabrial_oven_control/items/record_setpoint/record_setpoint_widget.py
fabrial_oven_control/items/record_setpoint/tag-label-green.png
fabrial_oven_control/items/record_temperature/__init__.py
fabrial_oven_control/items/record_temperature/record_temperature_item.py
fabrial_oven_control/items/record_temperature/record_temperature_step.py
fabrial_oven_control/items/record_temperature/record_temperature_widget.py
fabrial_oven_control/items/record_temperature/tag-label-red.png
fabrial_oven_control/items/set_setpoint/__init__.py
fabrial_oven_control/items/set_setpoint/set_setpoint_item.py
fabrial_oven_control/items/set_setpoint/set_setpoint_step.py
fabrial_oven_control/items/set_setpoint/set_setpoint_widget.py
fabrial_oven_control/items/set_setpoint/thermometer--arrow.png
fabrial_oven_control/items/set_setpoint/descriptions/data_recording.toml
fabrial_oven_control/items/set_setpoint/descriptions/overview.md
fabrial_oven_control-0.1.3.dist-info/METADATA
fabrial_oven_control-0.1.3.dist-info/WHEEL
fabrial_oven_control-0.1.3.dist-info/entry_points.txt
fabrial_oven_control-0.1.3.dist-info/licenses/LICENSE
fabrial_oven_control-0.1.3.dist-info/RECORD
