Metadata-Version: 2.4
Name: fabrial-oven-control
Version: 0.1.3
Summary: Fabrial plugin for controlling a Quincy 10 GCE lab oven, plus an oven interface and utility functions other plugins can use to control other ovens.
Project-URL: Repository, https://github.com/Maughan-Lab/fabrial-oven-control
Author-email: Drew Whitney <drewlwhitney@gmail.com>
Maintainer-email: Drew Whitney <drewlwhitney@gmail.com>
License-File: LICENSE
Requires-Python: >=3.13
Requires-Dist: fabrial
Requires-Dist: minimalmodbus>=2.1.1
Requires-Dist: pyqt6>=6.9.1
Requires-Dist: pyserial==3.5
